mrainet/__init__.py
mrainet/_version.py
mrainet/demo_mrai.py
mrainet/mraicnn.py
mrainet/mraidn.py
mrainet/mraidnn.py
mrainet/util.py
mrainet/viz.py
mrainet-0.1.0.dist-info/METADATA
mrainet-0.1.0.dist-info/RECORD
mrainet-0.1.0.dist-info/WHEEL
mrainet-0.1.0.dist-info/top_level.txt
