Metadata-Version: 2.1
Name: mrainet
Version: 0.1.0
Summary: MR acquisition-invariant network.
Home-page: https://github.com/wmkouw/mrai-net
Author: Wouter Kouw
Author-email: wmkouw@gmail.com
License: Apache 2.0
Platform: UNKNOWN
Classifier: Topic :: Scientific/Engineering :: Artificial Intelligence
Classifier: Topic :: Scientific/Engineering :: Image Recognition
Classifier: License :: OSI Approved :: MIT License
Classifier: Development Status :: 3 - Alpha
Classifier: Operating System :: POSIX :: Linux
Classifier: Programming Language :: Python :: 3.5
Classifier: Programming Language :: Python :: 3.6
Requires-Dist: numpy (>=1.12.1)
Requires-Dist: numpydoc (>=0.7.0)
Requires-Dist: scipy (>=0.11)
Requires-Dist: matplotlib (>=2.0.2)
Requires-Dist: ipython (>=5.5.0)
Requires-Dist: Sphinx (>=1.6.6)
Requires-Dist: nibabel (>=2.2.1)
Requires-Dist: scikit-learn (>=0.15.0)
Requires-Dist: tensorflow (>=0.12.1)
Requires-Dist: Keras (>=2.0.0)
